{
  "slug": "canadian-natural-cnq",
  "ticker": "CNQ",
  "exchange": "TSX: CNQ · NYSE: CNQ",
  "name": "Canadian Natural Resources Limited",
  "short_name": "Canadian Natural",
  "url": "https://www.cnrl.com/",
  "sector": "Energy",
  "sub_industry": "Oil & Gas",
  "page_eyebrow": "On the desk · Oil &amp; Gas",
  "headline_html": "Canadian Natural Resources: The <em>owner-operator</em> arithmetic.",
  "page_title": "Canadian Natural Resources (CNQ) — The owner-operator arithmetic | Halvren Capital",
  "meta_description": "Canadian Natural Resources has built a business that does not need $100 oil to matter. Halvren's read on the owner-operator arithmetic, the 26-year dividend streak, and the succession question.",
  "og_title": "Canadian Natural Resources (CNQ) — The owner-operator arithmetic",
  "og_description": "Halvren's read on CNQ. Low-decline assets, 26 years of dividend raises, $9B of shareholder returns, and the succession question.",
  "og_image": "/og-research-cnq.png",
  "published_iso": "2026-04-18",
  "modified_iso": "2026-04-18",
  "the_read": {
    "summary": "Canada's largest heavy-oil and natural-gas producer. Low corporate decline (10–14%) drives free-cash margin. FY 2025 production 1,571 MBOE/d, adj. funds flow C$15.5B, 26 consecutive dividend raises. Edwards as Executive Chair; Stauth as President since 2023.",
    "generated_iso": "2026-05-06",
    "source_filing": "CNQ FY 2025 earnings release (March 2026) and corporate disclosure",
    "principal_reviewed_iso": "2026-05-06"
  },
  "fy_snapshot": {
    "period": "FY 2025",
    "metrics": [
      {
        "label": "Production",
        "value": "1,571 MBOE/d (+15% YoY, record)"
      },
      {
        "label": "Liquids production",
        "value": "1,146 Mbbl/d (65% SCO/light/NGLs)"
      },
      {
        "label": "Adj. funds flow",
        "value": "C$15.5B ($7.39/sh)"
      },
      {
        "label": "Adj. net earnings",
        "value": "C$7.4B ($3.56/sh)"
      },
      {
        "label": "Shareholder returns",
        "value": "C$9.0B (div + buyback + debt)"
      },
      {
        "label": "2026 dividend",
        "value": "C$2.50/sh (26th consec. raise)"
      },
      {
        "label": "Leadership",
        "value": "Edwards (Exec Chair) · Stauth (Pres)"
      },
      {
        "label": "Listings",
        "value": "TSX: CNQ · NYSE: CNQ"
      }
    ]
  },
  "guidance": null,
  "leadership": {
    "ceo": "Scott Stauth",
    "ceo_since": 2023,
    "chair": "Murray Edwards (Executive Chairman)",
    "succession_visible": true,
    "note": "Stauth (former COO Oil Sands) succeeded Tim McKay as President in 2023; Edwards remains Executive Chairman and meaningfully invested."
  },
  "what_we_track": [
    "Sustaining capex",
    "Free cash flow at strip",
    "Buyback pace",
    "Insider alignment",
    "Succession"
  ],
  "checklist": {
    "scoring": [
      {
        "q": 1,
        "status": null,
        "note": null
      },
      {
        "q": 2,
        "status": null,
        "note": null
      },
      {
        "q": 3,
        "status": null,
        "note": null
      },
      {
        "q": 4,
        "status": null,
        "note": null
      },
      {
        "q": 5,
        "status": null,
        "note": null
      },
      {
        "q": 6,
        "status": null,
        "note": null
      },
      {
        "q": 7,
        "status": null,
        "note": null
      },
      {
        "q": 8,
        "status": null,
        "note": null
      },
      {
        "q": 9,
        "status": null,
        "note": null
      },
      {
        "q": 10,
        "status": null,
        "note": null
      }
    ],
    "pillar_commentary": {
      "I": "<strong>Pillar I. The business.</strong> FCF through the full cycle: yes, through 2015 and 2020, at significantly lower strip pricing than today. Unit economics at worst price: CNQ's corporate netback at US$40 WTI is still positive, a remarkably small set of public E&amp;Ps can say that. Balance sheet at trough: manageable, with the important caveat that the company carries more term debt than a pure defensive would, and leverage work matters. ROIC on incremental capital: AOSP and Duvernay are testing it in real time; the long-term track record on Horizon, Kirby, and the 2017 Shell deal is strong.",
      "II": "<strong>Pillar II. The people.</strong> This is the part of the deck most outsiders underweight. Insider ownership is meaningful and, importantly, has been <em>purchased</em> as well as granted across Edwards's 30+ years of tenure. Behaviour in 2015 and 2020 is the Canadian E&amp;P gold standard: CNQ did not cut the dividend in either downturn, did not issue equity, and used the depressed prints to acquire. Compensation is tied to per-share value and the dividend track, not to absolute production growth. Succession is visible but un-finished. On balance, very strong.",
      "III": "<strong>Pillar III. The cycle.</strong> CNQ is in the first quartile on the real North American oil cost curve, and the oil sands mining/SCO segment is structurally lower on the curve than most sell-side models capture because its decline rate is closer to zero than to 30%. The normal-decade question, &ldquo;does this still work at US$55 WTI in 2035?&rdquo;, reads affirmatively today. The bigger cycle question is the longer-dated one about oil demand and Canadian basin takeaway capacity, and that is where a lot of the honest work lives."
    }
  },
  "last_reviewed_iso": "2026-04-18",
  "next_earnings_iso": null,
  "position_disclosure": "may_hold",
  "disclosure_footnote_html": "This writeup is for informational and educational purposes only and is not a recommendation, solicitation, or price call. The author may hold a position in Canadian Natural Resources Limited and may transact at any time without notice. Figures are sourced from CNQ's FY 2025 earnings release (March 2026) and corporate disclosure. See the <a href=\"/terms\">Terms of Use</a> for the full disclaimer. Halvren's companion writeup of CNQ may appear on <a href=\"https://substack.com/@halvrencapital\" target=\"_blank\" rel=\"noopener noreferrer\">Substack</a> at greater length.",
  "back_link": {
    "href": "/#watchlist",
    "label": "Back to the watchlist"
  },
  "related_slugs": [
    "enbridge-enb",
    "cameco-cco"
  ]
}
